event_local/__init__.py
event_local/constants_event_local.py
event_local/event.py
event_local/events_local.py
event_local/handler.py
event_local/holiday_local.py
event_local/validate_inputs.py
event_local-0.0.36.dist-info/METADATA
event_local-0.0.36.dist-info/WHEEL
event_local-0.0.36.dist-info/top_level.txt
event_local-0.0.36.dist-info/RECORD
