Metadata-Version: 2.4
Name: event-local
Version: 0.0.36
Summary: PyPI Package for Circles event-local Python
Home-page: https://github.com/circles-zone/event-local-python-package
Author: Circles
Author-email: info@circlez.ai
Classifier: Programming Language :: Python :: 3
Classifier: License :: Other/Proprietary License
Classifier: Operating System :: OS Independent
Requires-Dist: logger-local>=0.0.177
Requires-Dist: database-mysql-local
Requires-Dist: python-sdk-remote>=0.0.145
Requires-Dist: opensearch-local>=0.0.8
Requires-Dist: location-local>=0.0.130
Dynamic: author
Dynamic: author-email
Dynamic: classifier
Dynamic: description
Dynamic: description-content-type
Dynamic: home-page
Dynamic: requires-dist
Dynamic: summary
